{
"meta":{"test_sets":[],"test_metrics":[],"learn_metrics":[{"best_value":"Min","name":"Logloss"}],"launch_mode":"Train","parameters":"","iteration_count":500,"learn_sets":["learn"],"name":"experiment"},
"iterations":[
{"learn":[0.6690208585],"iteration":0,"passed_time":0.003505567582,"remaining_time":1.749278223},
{"learn":[0.6465957492],"iteration":1,"passed_time":0.004826019933,"remaining_time":1.201678963},
{"learn":[0.6258809333],"iteration":2,"passed_time":0.007576379781,"remaining_time":1.255153584},
{"learn":[0.6061114517],"iteration":3,"passed_time":0.01041429461,"remaining_time":1.291372532},
{"learn":[0.5873675627],"iteration":4,"passed_time":0.01323896889,"remaining_time":1.31065792},
{"learn":[0.571001913],"iteration":5,"passed_time":0.01615935347,"remaining_time":1.330453436},
{"learn":[0.5552521874],"iteration":6,"passed_time":0.01890505717,"remaining_time":1.331456169},
{"learn":[0.5406821382],"iteration":7,"passed_time":0.02190294511,"remaining_time":1.347031124},
{"learn":[0.5267381855],"iteration":8,"passed_time":0.02479310936,"remaining_time":1.352601855},
{"learn":[0.5144174239],"iteration":9,"passed_time":0.02843696947,"remaining_time":1.393411504},
{"learn":[0.5022792442],"iteration":10,"passed_time":0.03174063541,"remaining_time":1.41101552},
{"learn":[0.4907115861],"iteration":11,"passed_time":0.03474568687,"remaining_time":1.412991266},
{"learn":[0.4799467723],"iteration":12,"passed_time":0.03776097864,"remaining_time":1.414584354},
{"learn":[0.4699754154],"iteration":13,"passed_time":0.04066033902,"remaining_time":1.411494626},
{"learn":[0.4611631281],"iteration":14,"passed_time":0.04385263606,"remaining_time":1.417901899},
{"learn":[0.4527157428],"iteration":15,"passed_time":0.04672855385,"remaining_time":1.413538754},
{"learn":[0.4448465833],"iteration":16,"passed_time":0.04956937223,"remaining_time":1.40835334},
{"learn":[0.437373741],"iteration":17,"passed_time":0.05244928241,"remaining_time":1.404475229},
{"learn":[0.4302265317],"iteration":18,"passed_time":0.05536427219,"remaining_time":1.401590259},
{"learn":[0.4236269932],"iteration":19,"passed_time":0.05810799766,"remaining_time":1.394591944},
{"learn":[0.4174103456],"iteration":20,"passed_time":0.06088558934,"remaining_time":1.3887713},
{"learn":[0.4112002803],"iteration":21,"passed_time":0.0636640946,"remaining_time":1.383247146},
{"learn":[0.4057354647],"iteration":22,"passed_time":0.06648285535,"remaining_time":1.378796609},
{"learn":[0.4006651336],"iteration":23,"passed_time":0.06948411521,"remaining_time":1.378101618},
{"learn":[0.3956502653],"iteration":24,"passed_time":0.07225455177,"remaining_time":1.372836484},
{"learn":[0.3912954143],"iteration":25,"passed_time":0.07429227772,"remaining_time":1.354405371},
{"learn":[0.3871101679],"iteration":26,"passed_time":0.07721617221,"remaining_time":1.352712943},
{"learn":[0.3833624148],"iteration":27,"passed_time":0.08009309624,"remaining_time":1.350140765},
{"learn":[0.3795636495],"iteration":28,"passed_time":0.08286318832,"remaining_time":1.345812472},
{"learn":[0.3761384627],"iteration":29,"passed_time":0.08579130786,"remaining_time":1.344063823},
{"learn":[0.3728078954],"iteration":30,"passed_time":0.08905839004,"remaining_time":1.347367256},
{"learn":[0.3696083368],"iteration":31,"passed_time":0.09208696501,"remaining_time":1.346771863},
{"learn":[0.3665768866],"iteration":32,"passed_time":0.09531161068,"remaining_time":1.348803703},
{"learn":[0.3638660207],"iteration":33,"passed_time":0.09880238218,"remaining_time":1.354173826},
{"learn":[0.3615835601],"iteration":34,"passed_time":0.1027671303,"remaining_time":1.365334731},
{"learn":[0.3591075972],"iteration":35,"passed_time":0.1071362746,"remaining_time":1.380867539},
{"learn":[0.3570429484],"iteration":36,"passed_time":0.1112742898,"remaining_time":1.392432329},
{"learn":[0.3546638115],"iteration":37,"passed_time":0.1151933241,"remaining_time":1.400508309},
{"learn":[0.3527831283],"iteration":38,"passed_time":0.1193676944,"remaining_time":1.410987362},
{"learn":[0.350856407],"iteration":39,"passed_time":0.1234772475,"remaining_time":1.419988347},
{"learn":[0.348954369],"iteration":40,"passed_time":0.1269804336,"remaining_time":1.42156144},
{"learn":[0.3472911236],"iteration":41,"passed_time":0.1303566567,"remaining_time":1.421508304},
{"learn":[0.3451548558],"iteration":42,"passed_time":0.1333653346,"remaining_time":1.41739437},
{"learn":[0.3438031814],"iteration":43,"passed_time":0.1366800423,"remaining_time":1.416502256},
{"learn":[0.3421433019],"iteration":44,"passed_time":0.1395641308,"remaining_time":1.411148434},
{"learn":[0.3405146131],"iteration":45,"passed_time":0.1424296733,"remaining_time":1.40571895},
{"learn":[0.3390461791],"iteration":46,"passed_time":0.1453711828,"remaining_time":1.401130762},
{"learn":[0.3378838184],"iteration":47,"passed_time":0.148109023,"remaining_time":1.3946933},
{"learn":[0.336355172],"iteration":48,"passed_time":0.1511512343,"remaining_time":1.3912083},
{"learn":[0.3349849103],"iteration":49,"passed_time":0.1541248672,"remaining_time":1.387123805},
{"learn":[0.3336563858],"iteration":50,"passed_time":0.1570487412,"remaining_time":1.3826448},
{"learn":[0.3325917113],"iteration":51,"passed_time":0.1599288018,"remaining_time":1.377848138},
{"learn":[0.3311650893],"iteration":52,"passed_time":0.1628470628,"remaining_time":1.373445982},
{"learn":[0.3295521456],"iteration":53,"passed_time":0.165961652,"remaining_time":1.370720311},
{"learn":[0.3283405678],"iteration":54,"passed_time":0.1693403075,"remaining_time":1.370117034},
{"learn":[0.3270206077],"iteration":55,"passed_time":0.1722819742,"remaining_time":1.365949938},
{"learn":[0.3259912379],"iteration":56,"passed_time":0.1750149584,"remaining_time":1.360203975},
{"learn":[0.325067034],"iteration":57,"passed_time":0.177819977,"remaining_time":1.355110859},
{"learn":[0.3240192638],"iteration":58,"passed_time":0.1807519012,"remaining_time":1.351043872},
{"learn":[0.3227171056],"iteration":59,"passed_time":0.1838741162,"remaining_time":1.348410186},
{"learn":[0.3216362374],"iteration":60,"passed_time":0.1866430369,"remaining_time":1.343217921},
{"learn":[0.3208954755],"iteration":61,"passed_time":0.1896476274,"remaining_time":1.339768722},
{"learn":[0.3200289034],"iteration":62,"passed_time":0.1923815107,"remaining_time":1.334455876},
{"learn":[0.3188630272],"iteration":63,"passed_time":0.1952224389,"remaining_time":1.329952865},
{"learn":[0.3179483601],"iteration":64,"passed_time":0.1987841368,"remaining_time":1.330324608},
{"learn":[0.317268409],"iteration":65,"passed_time":0.2019852771,"remaining_time":1.328206216},
{"learn":[0.316206128],"iteration":66,"passed_time":0.2050061473,"remaining_time":1.324890475},
{"learn":[0.3155315624],"iteration":67,"passed_time":0.2090009563,"remaining_time":1.327770781},
{"learn":[0.3146351833],"iteration":68,"passed_time":0.2120992161,"remaining_time":1.324851625},
{"learn":[0.3139289407],"iteration":69,"passed_time":0.2149027402,"remaining_time":1.320116833},
{"learn":[0.3130325991],"iteration":70,"passed_time":0.2182021039,"remaining_time":1.318432431},
{"learn":[0.3119338914],"iteration":71,"passed_time":0.2211501346,"remaining_time":1.314614689},
{"learn":[0.3109639673],"iteration":72,"passed_time":0.2248553258,"remaining_time":1.315249645},
{"learn":[0.3101986343],"iteration":73,"passed_time":0.227920369,"remaining_time":1.312082124},
{"learn":[0.3094123018],"iteration":74,"passed_time":0.2306202307,"remaining_time":1.306847974},
{"learn":[0.3086333555],"iteration":75,"passed_time":0.2339443749,"remaining_time":1.305163355},
{"learn":[0.3080775878],"iteration":76,"passed_time":0.2367856922,"remaining_time":1.300783738},
{"learn":[0.3076031068],"iteration":77,"passed_time":0.2394537599,"remaining_time":1.29550624},
{"learn":[0.3069336461],"iteration":78,"passed_time":0.2423400604,"remaining_time":1.29145779},
{"learn":[0.3064205319],"iteration":79,"passed_time":0.2450865414,"remaining_time":1.286704342},
{"learn":[0.305849281],"iteration":80,"passed_time":0.2480706321,"remaining_time":1.283229566},
{"learn":[0.3050012962],"iteration":81,"passed_time":0.2509579687,"remaining_time":1.279273548},
{"learn":[0.3042575986],"iteration":82,"passed_time":0.2537667822,"remaining_time":1.274948773},
{"learn":[0.3037165847],"iteration":83,"passed_time":0.2572496106,"remaining_time":1.273998071},
{"learn":[0.3031252693],"iteration":84,"passed_time":0.2608841567,"remaining_time":1.27372853},
{"learn":[0.3025531395],"iteration":85,"passed_time":0.2649020507,"remaining_time":1.275226151},
{"learn":[0.3020372017],"iteration":86,"passed_time":0.268643875,"remaining_time":1.275286441},
{"learn":[0.3012325436],"iteration":87,"passed_time":0.2720427785,"remaining_time":1.273654827},
{"learn":[0.3003286287],"iteration":88,"passed_time":0.2748834488,"remaining_time":1.269405589},
{"learn":[0.2999440735],"iteration":89,"passed_time":0.2779497622,"remaining_time":1.266215583},
{"learn":[0.2993608363],"iteration":90,"passed_time":0.2808372515,"remaining_time":1.26222457},
{"learn":[0.2986120523],"iteration":91,"passed_time":0.2836521186,"remaining_time":1.257935482},
{"learn":[0.2978863436],"iteration":92,"passed_time":0.2867103334,"remaining_time":1.254743072},
{"learn":[0.2975308661],"iteration":93,"passed_time":0.2896412222,"remaining_time":1.251003577},
{"learn":[0.2971962573],"iteration":94,"passed_time":0.2925354338,"remaining_time":1.247124744},
{"learn":[0.296609168],"iteration":95,"passed_time":0.2952875144,"remaining_time":1.24266829},
{"learn":[0.2959573035],"iteration":96,"passed_time":0.2982683228,"remaining_time":1.239197259},
{"learn":[0.2951713824],"iteration":97,"passed_time":0.3012836445,"remaining_time":1.235877807},
{"learn":[0.294527353],"iteration":98,"passed_time":0.3041276827,"remaining_time":1.231870715},
{"learn":[0.2939211528],"iteration":99,"passed_time":0.3075390666,"remaining_time":1.230156267},
{"learn":[0.2933712754],"iteration":100,"passed_time":0.3113368873,"remaining_time":1.229934832},
{"learn":[0.2927513123],"iteration":101,"passed_time":0.3148509271,"remaining_time":1.228535971},
{"learn":[0.2920139724],"iteration":102,"passed_time":0.3178425581,"remaining_time":1.225082481},
{"learn":[0.2915957582],"iteration":103,"passed_time":0.3208886003,"remaining_time":1.221845055},
{"learn":[0.2911719341],"iteration":104,"passed_time":0.3235958713,"remaining_time":1.217336849},
{"learn":[0.2905975417],"iteration":105,"passed_time":0.3264200117,"remaining_time":1.213297025},
{"learn":[0.2897575229],"iteration":106,"passed_time":0.3293893054,"remaining_time":1.209813056},
{"learn":[0.2893771003],"iteration":107,"passed_time":0.3331202272,"remaining_time":1.209103047},
{"learn":[0.2888625089],"iteration":108,"passed_time":0.3361488284,"remaining_time":1.205818274},
{"learn":[0.2882166844],"iteration":109,"passed_time":0.3390934395,"remaining_time":1.202240377},
{"learn":[0.2878179737],"iteration":110,"passed_time":0.342268329,"remaining_time":1.199480901},
{"learn":[0.2873506172],"iteration":111,"passed_time":0.3452414542,"remaining_time":1.196015038},
{"learn":[0.2866869908],"iteration":112,"passed_time":0.3481078301,"remaining_time":1.192192303},
{"learn":[0.2863925859],"iteration":113,"passed_time":0.3515113434,"remaining_time":1.190205075},
{"learn":[0.2858585096],"iteration":114,"passed_time":0.3550435798,"remaining_time":1.188624158},
{"learn":[0.2854385002],"iteration":115,"passed_time":0.3580320903,"remaining_time":1.185209678},
{"learn":[0.285011385],"iteration":116,"passed_time":0.3613143029,"remaining_time":1.182763915},
{"learn":[0.2844228558],"iteration":117,"passed_time":0.3650923887,"remaining_time":1.181909258},
{"learn":[0.2839789671],"iteration":118,"passed_time":0.3684869194,"remaining_time":1.179777448},
{"learn":[0.2834000307],"iteration":119,"passed_time":0.3716838625,"remaining_time":1.176998898},
{"learn":[0.2828969207],"iteration":120,"passed_time":0.3748269433,"remaining_time":1.174044723},
{"learn":[0.2822360244],"iteration":121,"passed_time":0.3777714107,"remaining_time":1.170472076},
{"learn":[0.2816695793],"iteration":122,"passed_time":0.3807885578,"remaining_time":1.167132409},
{"learn":[0.2811960894],"iteration":123,"passed_time":0.3836826037,"remaining_time":1.163424669},
{"learn":[0.2805924509],"iteration":124,"passed_time":0.3865713124,"remaining_time":1.159713937},
{"learn":[0.2801597072],"iteration":125,"passed_time":0.3896305942,"remaining_time":1.156522557},
{"learn":[0.2796903872],"iteration":126,"passed_time":0.3933599119,"remaining_time":1.155301159},
{"learn":[0.2792098101],"iteration":127,"passed_time":0.3970668758,"remaining_time":1.153975608},
{"learn":[0.2786911235],"iteration":128,"passed_time":0.4005734671,"remaining_time":1.152036871},
{"learn":[0.2780125749],"iteration":129,"passed_time":0.4043469262,"remaining_time":1.150833559},
{"learn":[0.2777122797],"iteration":130,"passed_time":0.4081998035,"remaining_time":1.149814714},
{"learn":[0.2771476297],"iteration":131,"passed_time":0.411621928,"remaining_time":1.147552042},
{"learn":[0.2767537435],"iteration":132,"passed_time":0.4148609433,"remaining_time":1.144766663},
{"learn":[0.2765935636],"iteration":133,"passed_time":0.4175890088,"remaining_time":1.140578935},
{"learn":[0.2762371886],"iteration":134,"passed_time":0.4206284449,"remaining_time":1.137254684},
{"learn":[0.2756814957],"iteration":135,"passed_time":0.4235608593,"remaining_time":1.133648182},
{"learn":[0.2752048642],"iteration":136,"passed_time":0.4264464188,"remaining_time":1.129927372},
{"learn":[0.2748290417],"iteration":137,"passed_time":0.4292769025,"remaining_time":1.126074194},
{"learn":[0.2743425556],"iteration":138,"passed_time":0.4325031051,"remaining_time":1.12326346},
{"learn":[0.2737738665],"iteration":139,"passed_time":0.4361452126,"remaining_time":1.121516261},
{"learn":[0.2732194078],"iteration":140,"passed_time":0.4390859525,"remaining_time":1.117956432},
{"learn":[0.2727758931],"iteration":141,"passed_time":0.4419026971,"remaining_time":1.114092715},
{"learn":[0.2722967559],"iteration":142,"passed_time":0.445514544,"remaining_time":1.112228617},
{"learn":[0.2718558592],"iteration":143,"passed_time":0.4484652644,"remaining_time":1.108705793},
{"learn":[0.2710184583],"iteration":144,"passed_time":0.4513255971,"remaining_time":1.104969565},
{"learn":[0.2706205331],"iteration":145,"passed_time":0.4541350452,"remaining_time":1.101121959},
{"learn":[0.2700144824],"iteration":146,"passed_time":0.457037883,"remaining_time":1.097512739},
{"learn":[0.2697060529],"iteration":147,"passed_time":0.4600439598,"remaining_time":1.094158607},
{"learn":[0.2692078235],"iteration":148,"passed_time":0.4634819581,"remaining_time":1.091826626},
{"learn":[0.2685560713],"iteration":149,"passed_time":0.4666139283,"remaining_time":1.088765833},
{"learn":[0.2681686177],"iteration":150,"passed_time":0.4700015074,"remaining_time":1.086294875},
{"learn":[0.2678380106],"iteration":151,"passed_time":0.4733030558,"remaining_time":1.083614891},
{"learn":[0.2672702752],"iteration":152,"passed_time":0.476220756,"remaining_time":1.080056224},
{"learn":[0.2669932048],"iteration":153,"passed_time":0.4789520548,"remaining_time":1.076087084},
{"learn":[0.2664951624],"iteration":154,"passed_time":0.4817800238,"remaining_time":1.072349085},
{"learn":[0.2659845165],"iteration":155,"passed_time":0.4846675853,"remaining_time":1.068754162},
{"learn":[0.2654274585],"iteration":156,"passed_time":0.4876094886,"remaining_time":1.065286972},
{"learn":[0.2650494669],"iteration":157,"passed_time":0.4904621653,"remaining_time":1.061633295},
{"learn":[0.2645642898],"iteration":158,"passed_time":0.4931811599,"remaining_time":1.057702991},
{"learn":[0.2642242581],"iteration":159,"passed_time":0.4965673987,"remaining_time":1.055205722},
{"learn":[0.2638449762],"iteration":160,"passed_time":0.4995131356,"remaining_time":1.051769894},
{"learn":[0.2632829442],"iteration":161,"passed_time":0.5023411868,"remaining_time":1.048094575},
{"learn":[0.2628122405],"iteration":162,"passed_time":0.5051830111,"remaining_time":1.044458127},
{"learn":[0.2625508028],"iteration":163,"passed_time":0.5079416031,"remaining_time":1.040660845},
{"learn":[0.2622633354],"iteration":164,"passed_time":0.5110050049,"remaining_time":1.03749501},
{"learn":[0.2618529563],"iteration":165,"passed_time":0.5138342829,"remaining_time":1.03385934},
{"learn":[0.2615112604],"iteration":166,"passed_time":0.5165949828,"remaining_time":1.030096583},
{"learn":[0.2612895405],"iteration":167,"passed_time":0.5193268668,"remaining_time":1.026288808},
{"learn":[0.2607165318],"iteration":168,"passed_time":0.5221301828,"remaining_time":1.022633672},
{"learn":[0.2602012111],"iteration":169,"passed_time":0.5251823525,"remaining_time":1.019471625},
{"learn":[0.25979014],"iteration":170,"passed_time":0.5281566283,"remaining_time":1.016160998},
{"learn":[0.2594057719],"iteration":171,"passed_time":0.5314094294,"remaining_time":1.013385424},
{"learn":[0.2588992025],"iteration":172,"passed_time":0.5353040146,"remaining_time":1.011817415},
{"learn":[0.2585558985],"iteration":173,"passed_time":0.5391519544,"remaining_time":1.010135271},
{"learn":[0.2580822776],"iteration":174,"passed_time":0.5434923368,"remaining_time":1.009342911},
{"learn":[0.2576412874],"iteration":175,"passed_time":0.5474409073,"remaining_time":1.007788943},
{"learn":[0.2570590973],"iteration":176,"passed_time":0.5510211002,"remaining_time":1.00553568},
{"learn":[0.2566505881],"iteration":177,"passed_time":0.5547622379,"remaining_time":1.003558655},
{"learn":[0.2560464822],"iteration":178,"passed_time":0.5586194244,"remaining_time":1.001770029},
{"learn":[0.2556957918],"iteration":179,"passed_time":0.5623829907,"remaining_time":0.9997919836},
{"learn":[0.2553551618],"iteration":180,"passed_time":0.5661468079,"remaining_time":0.9977946503},
{"learn":[0.2549362557],"iteration":181,"passed_time":0.569268205,"remaining_time":0.9946554351},
{"learn":[0.2545704],"iteration":182,"passed_time":0.572142569,"remaining_time":0.9910884938},
{"learn":[0.2541973638],"iteration":183,"passed_time":0.5750168789,"remaining_time":0.9875289876},
{"learn":[0.2539517646],"iteration":184,"passed_time":0.5778510649,"remaining_time":0.98390857},
{"learn":[0.2536335178],"iteration":185,"passed_time":0.5806763526,"remaining_time":0.9802815845},
{"learn":[0.2532023636],"iteration":186,"passed_time":0.583832733,"remaining_time":0.9772173552},
{"learn":[0.2527152791],"iteration":187,"passed_time":0.5869211234,"remaining_time":0.9740393113},
{"learn":[0.2525635514],"iteration":188,"passed_time":0.5899070497,"remaining_time":0.9706936109},
{"learn":[0.2522720262],"iteration":189,"passed_time":0.5928861055,"remaining_time":0.967340488},
{"learn":[0.2517821929],"iteration":190,"passed_time":0.5958565807,"remaining_time":0.9639774002},
{"learn":[0.2514585981],"iteration":191,"passed_time":0.5989859623,"remaining_time":0.9608733145},
{"learn":[0.2509809382],"iteration":192,"passed_time":0.6019162964,"remaining_time":0.9574523471},
{"learn":[0.250697753],"iteration":193,"passed_time":0.6046808601,"remaining_time":0.9537749648},
{"learn":[0.2503209956],"iteration":194,"passed_time":0.6075888737,"remaining_time":0.9503313152},
{"learn":[0.2500226264],"iteration":195,"passed_time":0.6111852479,"remaining_time":0.9479607927},
{"learn":[0.24970797],"iteration":196,"passed_time":0.6151827684,"remaining_time":0.9461948164},
{"learn":[0.2491656659],"iteration":197,"passed_time":0.6192447713,"remaining_time":0.9445046511},
{"learn":[0.2487900304],"iteration":198,"passed_time":0.6229277705,"remaining_time":0.9422173815},
{"learn":[0.2483748081],"iteration":199,"passed_time":0.6269700562,"remaining_time":0.9404550843},
{"learn":[0.24804594],"iteration":200,"passed_time":0.630746758,"remaining_time":0.9382750281},
{"learn":[0.2477167167],"iteration":201,"passed_time":0.6337279697,"remaining_time":0.9349056186},
{"learn":[0.2473868202],"iteration":202,"passed_time":0.6364433379,"remaining_time":0.9311510904},
{"learn":[0.2470894982],"iteration":203,"passed_time":0.6391680795,"remaining_time":0.9274203506},
{"learn":[0.2467300191],"iteration":204,"passed_time":0.6424299552,"remaining_time":0.9244723746},
{"learn":[0.2464410931],"iteration":205,"passed_time":0.6453818561,"remaining_time":0.9210789597},
{"learn":[0.2462174846],"iteration":206,"passed_time":0.6484942421,"remaining_time":0.9179169708},
{"learn":[0.2457107469],"iteration":207,"passed_time":0.6521864288,"remaining_time":0.9155694097},
{"learn":[0.2453854131],"iteration":208,"passed_time":0.65608741,"remaining_time":0.9134996953},
{"learn":[0.2450630525],"iteration":209,"passed_time":0.6597435974,"remaining_time":0.9110744917},
{"learn":[0.2446622288],"iteration":210,"passed_time":0.6636533537,"remaining_time":0.9089849252},
{"learn":[0.2443859998],"iteration":211,"passed_time":0.6669496718,"remaining_time":0.9060448372},
{"learn":[0.2439698612],"iteration":212,"passed_time":0.6696404579,"remaining_time":0.9022854996},
{"learn":[0.2436131496],"iteration":213,"passed_time":0.6724715826,"remaining_time":0.8987237038},
{"learn":[0.243398816],"iteration":214,"passed_time":0.6754943568,"remaining_time":0.8954227521},
{"learn":[0.2430352417],"iteration":215,"passed_time":0.6782401095,"remaining_time":0.891760144},
{"learn":[0.2426852806],"iteration":216,"passed_time":0.6811277231,"remaining_time":0.8882909937},
{"learn":[0.2423617232],"iteration":217,"passed_time":0.6839160849,"remaining_time":0.8846987887},
{"learn":[0.242091609],"iteration":218,"passed_time":0.6866863251,"remaining_time":0.8810906728},
{"learn":[0.2416744045],"iteration":219,"passed_time":0.6898602003,"remaining_time":0.8780038913},
{"learn":[0.2413530537],"iteration":220,"passed_time":0.6927070433,"remaining_time":0.8745034619},
{"learn":[0.2409534828],"iteration":221,"passed_time":0.6955787884,"remaining_time":0.8710401045},
{"learn":[0.2405983794],"iteration":222,"passed_time":0.6983548515,"remaining_time":0.8674632012},
{"learn":[0.2401613909],"iteration":223,"passed_time":0.7012418271,"remaining_time":0.8640301084},
{"learn":[0.2396547654],"iteration":224,"passed_time":0.7040048148,"remaining_time":0.8604503292},
{"learn":[0.2393372667],"iteration":225,"passed_time":0.7071487873,"remaining_time":0.8573396802},
{"learn":[0.2389994603],"iteration":226,"passed_time":0.7099566386,"remaining_time":0.8538245037},
{"learn":[0.2387229321],"iteration":227,"passed_time":0.7128402924,"remaining_time":0.8504059628},
{"learn":[0.2385763655],"iteration":228,"passed_time":0.7162373362,"remaining_time":0.8475996424},
{"learn":[0.2382155774],"iteration":229,"passed_time":0.7199138404,"remaining_time":0.8451162474},
{"learn":[0.2378828011],"iteration":230,"passed_time":0.723010271,"remaining_time":0.8419470255},
{"learn":[0.2375252668],"iteration":231,"passed_time":0.7258085958,"remaining_time":0.8384340675},
{"learn":[0.2371971654],"iteration":232,"passed_time":0.7288827344,"remaining_time":0.8352433051},
{"learn":[0.2369357464],"iteration":233,"passed_time":0.7317132544,"remaining_time":0.8317766054},
{"learn":[0.2368413888],"iteration":234,"passed_time":0.7344713321,"remaining_time":0.8282336298},
{"learn":[0.2360891454],"iteration":235,"passed_time":0.7374023024,"remaining_time":0.8248907112},
{"learn":[0.2357222239],"iteration":236,"passed_time":0.7402627611,"remaining_time":0.8214730218},
{"learn":[0.2354955112],"iteration":237,"passed_time":0.7434910227,"remaining_time":0.8184649074},
{"learn":[0.23516367],"iteration":238,"passed_time":0.7472222552,"remaining_time":0.8160042201},
{"learn":[0.2347805734],"iteration":239,"passed_time":0.7508216878,"remaining_time":0.8133901618},
{"learn":[0.2345817603],"iteration":240,"passed_time":0.7547166262,"remaining_time":0.8110855028},
{"learn":[0.2341382831],"iteration":241,"passed_time":0.7585104118,"remaining_time":0.8086598605},
{"learn":[0.2338007572],"iteration":242,"passed_time":0.7617430758,"remaining_time":0.8056295082},
{"learn":[0.2333630394],"iteration":243,"passed_time":0.7651125091,"remaining_time":0.8027409931},
{"learn":[0.2330142376],"iteration":244,"passed_time":0.7689909975,"remaining_time":0.8003783852},
{"learn":[0.2328353209],"iteration":245,"passed_time":0.7725584615,"remaining_time":0.7976823139},
{"learn":[0.2324328703],"iteration":246,"passed_time":0.7762677958,"remaining_time":0.7951245034},
{"learn":[0.2320483713],"iteration":247,"passed_time":0.7798653268,"remaining_time":0.7924437998},
{"learn":[0.2319189707],"iteration":248,"passed_time":0.7828682187,"remaining_time":0.7891563168},
{"learn":[0.2315393149],"iteration":249,"passed_time":0.7855991334,"remaining_time":0.7855991334},
{"learn":[0.231067938],"iteration":250,"passed_time":0.7889844864,"remaining_time":0.7826977575},
{"learn":[0.2306618036],"iteration":251,"passed_time":0.7923155568,"remaining_time":0.7797391194},
{"learn":[0.2304106881],"iteration":252,"passed_time":0.7959023582,"remaining_time":0.7770272035},
{"learn":[0.2301765143],"iteration":253,"passed_time":0.7991464367,"remaining_time":0.7739764701},
{"learn":[0.2299447527],"iteration":254,"passed_time":0.802027998,"remaining_time":0.7705759197},
{"learn":[0.2295916127],"iteration":255,"passed_time":0.8048696333,"remaining_time":0.7671413692},
{"learn":[0.2290501688],"iteration":256,"passed_time":0.8079084395,"remaining_time":0.763897863},
{"learn":[0.2286781984],"iteration":257,"passed_time":0.8108155688,"remaining_time":0.7605324327},
{"learn":[0.2281560711],"iteration":258,"passed_time":0.8139792201,"remaining_time":0.7574092357},
{"learn":[0.227692735],"iteration":259,"passed_time":0.8173236052,"remaining_time":0.7544525587},
{"learn":[0.2273389031],"iteration":260,"passed_time":0.8202101686,"remaining_time":0.7510736793},
{"learn":[0.2269253824],"iteration":261,"passed_time":0.822998799,"remaining_time":0.747609596},
{"learn":[0.2265234742],"iteration":262,"passed_time":0.8258605328,"remaining_time":0.7442165257},
{"learn":[0.2263439403],"iteration":263,"passed_time":0.8286470503,"remaining_time":0.7407602419},
{"learn":[0.2261233423],"iteration":264,"passed_time":0.8315120949,"remaining_time":0.7373786502},
{"learn":[0.2257897994],"iteration":265,"passed_time":0.8343230331,"remaining_time":0.7339533449},
{"learn":[0.2255477905],"iteration":266,"passed_time":0.8376251217,"remaining_time":0.7309612485},
{"learn":[0.2253262015],"iteration":267,"passed_time":0.8405983321,"remaining_time":0.7276821383},
{"learn":[0.224797361],"iteration":268,"passed_time":0.8436628956,"remaining_time":0.7244837505},
{"learn":[0.2244879405],"iteration":269,"passed_time":0.846787202,"remaining_time":0.7213372461},
{"learn":[0.2241090887],"iteration":270,"passed_time":0.8497987599,"remaining_time":0.7180956311},
{"learn":[0.2237707213],"iteration":271,"passed_time":0.8529462457,"remaining_time":0.7149696471},
{"learn":[0.2235001209],"iteration":272,"passed_time":0.8562401216,"remaining_time":0.7119652293},
{"learn":[0.2231379303],"iteration":273,"passed_time":0.8591627318,"remaining_time":0.7086524722},
{"learn":[0.2227324691],"iteration":274,"passed_time":0.861948785,"remaining_time":0.7052308241},
{"learn":[0.2223624996],"iteration":275,"passed_time":0.8650363438,"remaining_time":0.7020584819},
{"learn":[0.2220411114],"iteration":276,"passed_time":0.8680967332,"remaining_time":0.6988648791},
{"learn":[0.2213435454],"iteration":277,"passed_time":0.8709132116,"remaining_time":0.6954774567},
{"learn":[0.2210214278],"iteration":278,"passed_time":0.8738353833,"remaining_time":0.6921778485},
{"learn":[0.220522357],"iteration":279,"passed_time":0.8766665282,"remaining_time":0.688809415},
{"learn":[0.2200655844],"iteration":280,"passed_time":0.8796400136,"remaining_time":0.6855557401},
{"learn":[0.2197559207],"iteration":281,"passed_time":0.8824995506,"remaining_time":0.6822159647},
{"learn":[0.2194469676],"iteration":282,"passed_time":0.8853784025,"remaining_time":0.6788943934},
{"learn":[0.2190904991],"iteration":283,"passed_time":0.8888010024,"remaining_time":0.6759894948},
{"learn":[0.2188004886],"iteration":284,"passed_time":0.8916552081,"remaining_time":0.6726521745},
{"learn":[0.218564875],"iteration":285,"passed_time":0.8945616581,"remaining_time":0.6693573246},
{"learn":[0.2182911892],"iteration":286,"passed_time":0.8980355103,"remaining_time":0.6664862846},
{"learn":[0.217865813],"iteration":287,"passed_time":0.901799649,"remaining_time":0.6638247417},
{"learn":[0.2175856946],"iteration":288,"passed_time":0.9098415933,"remaining_time":0.6642788103},
{"learn":[0.2171616087],"iteration":289,"passed_time":0.9127545555,"remaining_time":0.6609601953},
{"learn":[0.2164413228],"iteration":290,"passed_time":0.9156442936,"remaining_time":0.6576276886},
{"learn":[0.2160484838],"iteration":291,"passed_time":0.9185605757,"remaining_time":0.6543171224},
{"learn":[0.2156196669],"iteration":292,"passed_time":0.9218829458,"remaining_time":0.6512961426},
{"learn":[0.2153213538],"iteration":293,"passed_time":0.9247969415,"remaining_time":0.6479869726},
{"learn":[0.2151347516],"iteration":294,"passed_time":0.9276809286,"remaining_time":0.6446596284},
{"learn":[0.2149957021],"iteration":295,"passed_time":0.9311085094,"remaining_time":0.6417099186},
{"learn":[0.2146318847],"iteration":296,"passed_time":0.934158922,"remaining_time":0.6384991959},
{"learn":[0.2143962524],"iteration":297,"passed_time":0.9374872221,"remaining_time":0.6354779157},
{"learn":[0.2140533597],"iteration":298,"passed_time":0.940450706,"remaining_time":0.6322093375},
{"learn":[0.2137054369],"iteration":299,"passed_time":0.9433144113,"remaining_time":0.6288762742},
{"learn":[0.2133201524],"iteration":300,"passed_time":0.9461332694,"remaining_time":0.6255166798},
{"learn":[0.2131023407],"iteration":301,"passed_time":0.9489286581,"remaining_time":0.6221452791},
{"learn":[0.2127197864],"iteration":302,"passed_time":0.9517584787,"remaining_time":0.618800067},
{"learn":[0.212329397],"iteration":303,"passed_time":0.9552249478,"remaining_time":0.6158687163},
{"learn":[0.2119246464],"iteration":304,"passed_time":0.9594116632,"remaining_time":0.613394342},
{"learn":[0.2117316863],"iteration":305,"passed_time":0.9625906686,"remaining_time":0.610269901},
{"learn":[0.2115188486],"iteration":306,"passed_time":0.965549213,"remaining_time":0.6070065085},
{"learn":[0.2112214332],"iteration":307,"passed_time":0.9684409969,"remaining_time":0.6037034786},
{"learn":[0.2109742445],"iteration":308,"passed_time":0.9713097844,"remaining_time":0.6003888958},
{"learn":[0.2109298519],"iteration":309,"passed_time":0.9741989699,"remaining_time":0.5970896912},
{"learn":[0.2108014425],"iteration":310,"passed_time":0.9769694243,"remaining_time":0.5937209684},
{"learn":[0.2103824989],"iteration":311,"passed_time":0.9799451461,"remaining_time":0.5904797675},
{"learn":[0.2099776735],"iteration":312,"passed_time":0.9831163512,"remaining_time":0.5873570532},
{"learn":[0.2098358005],"iteration":313,"passed_time":0.9860234717,"remaining_time":0.5840775979},
{"learn":[0.2093596552],"iteration":314,"passed_time":0.9888688173,"remaining_time":0.580764226},
{"learn":[0.2089900035],"iteration":315,"passed_time":0.9918627129,"remaining_time":0.5775403138},
{"learn":[0.2086931864],"iteration":316,"passed_time":0.9948786328,"remaining_time":0.5743305672},
{"learn":[0.2083076776],"iteration":317,"passed_time":0.9977095003,"remaining_time":0.5710161291},
{"learn":[0.207974303],"iteration":318,"passed_time":1.00057398,"remaining_time":0.5677237944},
{"learn":[0.2075118271],"iteration":319,"passed_time":1.003379022,"remaining_time":0.5644006996},
{"learn":[0.2073252809],"iteration":320,"passed_time":1.006197377,"remaining_time":0.561088257},
{"learn":[0.2069618001],"iteration":321,"passed_time":1.009133972,"remaining_time":0.5578442453},
{"learn":[0.2067936542],"iteration":322,"passed_time":1.011985845,"remaining_time":0.554555711},
{"learn":[0.2064908346],"iteration":323,"passed_time":1.015013182,"remaining_time":0.551365185},
{"learn":[0.2064088373],"iteration":324,"passed_time":1.017868933,"remaining_time":0.5480832718},
{"learn":[0.2061748131],"iteration":325,"passed_time":1.02086416,"remaining_time":0.5448784166},
{"learn":[0.2057774488],"iteration":326,"passed_time":1.023766571,"remaining_time":0.5416257396},
{"learn":[0.2054371927],"iteration":327,"passed_time":1.026637194,"remaining_time":0.5383585285},
{"learn":[0.2049745672],"iteration":328,"passed_time":1.029616525,"remaining_time":0.5351502303},
{"learn":[0.204788208],"iteration":329,"passed_time":1.032644869,"remaining_time":0.531968569},
{"learn":[0.2043866176],"iteration":330,"passed_time":1.035741101,"remaining_time":0.5288224957},
{"learn":[0.2041077333],"iteration":331,"passed_time":1.038426272,"remaining_time":0.5254687162},
{"learn":[0.2037299661],"iteration":332,"passed_time":1.041698753,"remaining_time":0.522413489},
{"learn":[0.2034973631],"iteration":333,"passed_time":1.0447179,"remaining_time":0.5192310521},
{"learn":[0.2032089046],"iteration":334,"passed_time":1.04764443,"remaining_time":0.5160039732},
{"learn":[0.202738631],"iteration":335,"passed_time":1.050490265,"remaining_time":0.512739296},
{"learn":[0.2024312861],"iteration":336,"passed_time":1.054090803,"remaining_time":0.5098421392},
{"learn":[0.2021208744],"iteration":337,"passed_time":1.057446205,"remaining_time":0.5068233292},
{"learn":[0.2017215654],"iteration":338,"passed_time":1.060807232,"remaining_time":0.5038052045},
{"learn":[0.2015302882],"iteration":339,"passed_time":1.064175702,"remaining_time":0.5007885657},
{"learn":[0.2013974844],"iteration":340,"passed_time":1.06709565,"remaining_time":0.4975607284},
{"learn":[0.2012919632],"iteration":341,"passed_time":1.070338684,"remaining_time":0.4944839534},
{"learn":[0.2012249442],"iteration":342,"passed_time":1.073551911,"remaining_time":0.4913925659},
{"learn":[0.2009279401],"iteration":343,"passed_time":1.076615489,"remaining_time":0.4882326055},
{"learn":[0.2006571527],"iteration":344,"passed_time":1.079499298,"remaining_time":0.4849924384},
{"learn":[0.2005848791],"iteration":345,"passed_time":1.082234578,"remaining_time":0.4816882226},
{"learn":[0.2002436694],"iteration":346,"passed_time":1.085091898,"remaining_time":0.4784410961},
{"learn":[0.1998788796],"iteration":347,"passed_time":1.088220512,"remaining_time":0.4753147065},
{"learn":[0.1997034409],"iteration":348,"passed_time":1.09124615,"remaining_time":0.4721437496},
{"learn":[0.1992844413],"iteration":349,"passed_time":1.094460944,"remaining_time":0.4690546901},
{"learn":[0.1991165012],"iteration":350,"passed_time":1.097362015,"remaining_time":0.4658317384},
{"learn":[0.1989167531],"iteration":351,"passed_time":1.100668203,"remaining_time":0.4627809488},
{"learn":[0.1985782548],"iteration":352,"passed_time":1.103558523,"remaining_time":0.4595555321},
{"learn":[0.1982264799],"iteration":353,"passed_time":1.106475794,"remaining_time":0.456343124},
{"learn":[0.1978254131],"iteration":354,"passed_time":1.109243584,"remaining_time":0.4530713229},
{"learn":[0.1975962134],"iteration":355,"passed_time":1.112225344,"remaining_time":0.449888903},
{"learn":[0.1972539565],"iteration":356,"passed_time":1.115396748,"remaining_time":0.4467835712},
{"learn":[0.1969696494],"iteration":357,"passed_time":1.118589246,"remaining_time":0.4436862371},
{"learn":[0.1968381171],"iteration":358,"passed_time":1.121484462,"remaining_time":0.4404716131},
{"learn":[0.1965068929],"iteration":359,"passed_time":1.124903486,"remaining_time":0.4374624667},
{"learn":[0.1962053262],"iteration":360,"passed_time":1.128627713,"remaining_time":0.4345685654},
{"learn":[0.1958303826],"iteration":361,"passed_time":1.132564528,"remaining_time":0.4317511185},
{"learn":[0.1954464445],"iteration":362,"passed_time":1.136565895,"remaining_time":0.4289518667},
{"learn":[0.1950729782],"iteration":363,"passed_time":1.140310948,"remaining_time":0.4260502443},
{"learn":[0.1945997687],"iteration":364,"passed_time":1.143580312,"remaining_time":0.4229680607},
{"learn":[0.1943209218],"iteration":365,"passed_time":1.146271603,"remaining_time":0.4196732097},
{"learn":[0.1941183876],"iteration":366,"passed_time":1.149035635,"remaining_time":0.4164080094},
{"learn":[0.1940533881],"iteration":367,"passed_time":1.152190235,"remaining_time":0.4132856279},
{"learn":[0.1936858308],"iteration":368,"passed_time":1.155120441,"remaining_time":0.4100834084},
{"learn":[0.1933386934],"iteration":369,"passed_time":1.158025391,"remaining_time":0.4068737862},
{"learn":[0.1929832907],"iteration":370,"passed_time":1.160925212,"remaining_time":0.4036640226},
{"learn":[0.1928046357],"iteration":371,"passed_time":1.163884259,"remaining_time":0.4004763042},
{"learn":[0.1926772174],"iteration":372,"passed_time":1.167226475,"remaining_time":0.3974202743},
{"learn":[0.1924937005],"iteration":373,"passed_time":1.170179329,"remaining_time":0.3942315387},
{"learn":[0.1921553518],"iteration":374,"passed_time":1.173072581,"remaining_time":0.3910241936},
{"learn":[0.1917883742],"iteration":375,"passed_time":1.17600413,"remaining_time":0.3878311493},
{"learn":[0.1916968028],"iteration":376,"passed_time":1.179679665,"remaining_time":0.384882225},
{"learn":[0.1913690006],"iteration":377,"passed_time":1.183220207,"remaining_time":0.3818858869},
{"learn":[0.1909434936],"iteration":378,"passed_time":1.186010202,"remaining_time":0.3786470567},
{"learn":[0.1905740289],"iteration":379,"passed_time":1.188966909,"remaining_time":0.3754632345},
{"learn":[0.1903129652],"iteration":380,"passed_time":1.191859389,"remaining_time":0.372260544},
{"learn":[0.1900858225],"iteration":381,"passed_time":1.194699218,"remaining_time":0.369043214},
{"learn":[0.1898481332],"iteration":382,"passed_time":1.198210328,"remaining_time":0.3660329201},
{"learn":[0.189497742],"iteration":383,"passed_time":1.201869528,"remaining_time":0.3630647532},
{"learn":[0.1890425776],"iteration":384,"passed_time":1.205880085,"remaining_time":0.3601979475},
{"learn":[0.1885977913],"iteration":385,"passed_time":1.209028063,"remaining_time":0.3570704641},
{"learn":[0.1883752112],"iteration":386,"passed_time":1.212280659,"remaining_time":0.3539734223},
{"learn":[0.188241809],"iteration":387,"passed_time":1.215580338,"remaining_time":0.3508891698},
{"learn":[0.1880101971],"iteration":388,"passed_time":1.218914405,"remaining_time":0.347813622},
{"learn":[0.1875664767],"iteration":389,"passed_time":1.222231437,"remaining_time":0.3447319438},
{"learn":[0.1874104294],"iteration":390,"passed_time":1.225179714,"remaining_time":0.341546263},
{"learn":[0.1872031081],"iteration":391,"passed_time":1.228156749,"remaining_time":0.3383697165},
{"learn":[0.1870081658],"iteration":392,"passed_time":1.231326503,"remaining_time":0.3352466559},
{"learn":[0.1866007038],"iteration":393,"passed_time":1.234296872,"remaining_time":0.3320697167},
{"learn":[0.1864868239],"iteration":394,"passed_time":1.237021446,"remaining_time":0.3288284857},
{"learn":[0.1861740187],"iteration":395,"passed_time":1.239825104,"remaining_time":0.3256106332},
{"learn":[0.1859259138],"iteration":396,"passed_time":1.242672184,"remaining_time":0.3224061334},
{"learn":[0.1858121835],"iteration":397,"passed_time":1.245596962,"remaining_time":0.319223342},
{"learn":[0.1854848675],"iteration":398,"passed_time":1.248541546,"remaining_time":0.3160468574},
{"learn":[0.1853378894],"iteration":399,"passed_time":1.251445225,"remaining_time":0.3128613062},
{"learn":[0.185037669],"iteration":400,"passed_time":1.254259291,"remaining_time":0.309655037},
{"learn":[0.18460874],"iteration":401,"passed_time":1.257180963,"remaining_time":0.3064769511},
{"learn":[0.1843587838],"iteration":402,"passed_time":1.260231869,"remaining_time":0.3033312438},
{"learn":[0.1842237734],"iteration":403,"passed_time":1.263075122,"remaining_time":0.3001366626},
{"learn":[0.1838921192],"iteration":404,"passed_time":1.265967669,"remaining_time":0.2969553792},
{"learn":[0.183668922],"iteration":405,"passed_time":1.268946908,"remaining_time":0.2937955894},
{"learn":[0.1833791359],"iteration":406,"passed_time":1.272390726,"remaining_time":0.2907428441},
{"learn":[0.1830466027],"iteration":407,"passed_time":1.275371173,"remaining_time":0.2875836959},
{"learn":[0.1826299032],"iteration":408,"passed_time":1.27878712,"remaining_time":0.2845223176},
{"learn":[0.182295257],"iteration":409,"passed_time":1.281644557,"remaining_time":0.2813366101},
{"learn":[0.1818909178],"iteration":410,"passed_time":1.284568698,"remaining_time":0.2781669442},
{"learn":[0.1816771077],"iteration":411,"passed_time":1.287404494,"remaining_time":0.2749796008},
{"learn":[0.1814627741],"iteration":412,"passed_time":1.29051205,"remaining_time":0.2718512067},
{"learn":[0.1811969233],"iteration":413,"passed_time":1.293887989,"remaining_time":0.2687786644},
{"learn":[0.1809012469],"iteration":414,"passed_time":1.297711062,"remaining_time":0.2657962416},
{"learn":[0.1806475695],"iteration":415,"passed_time":1.301327895,"remaining_time":0.2627681327},
{"learn":[0.1802268683],"iteration":416,"passed_time":1.304476884,"remaining_time":0.2596440801},
{"learn":[0.1798674453],"iteration":417,"passed_time":1.307855849,"remaining_time":0.256565023},
{"learn":[0.1795660281],"iteration":418,"passed_time":1.311547623,"remaining_time":0.2535450058},
{"learn":[0.1795345007],"iteration":419,"passed_time":1.314612015,"remaining_time":0.2504022886},
{"learn":[0.1790239297],"iteration":420,"passed_time":1.317435321,"remaining_time":0.2472147039},
{"learn":[0.1784716961],"iteration":421,"passed_time":1.320336387,"remaining_time":0.2440432185},
{"learn":[0.1782850378],"iteration":422,"passed_time":1.323193024,"remaining_time":0.240864924},
{"learn":[0.1776560802],"iteration":423,"passed_time":1.326107434,"remaining_time":0.2376985022},
{"learn":[0.1773806927],"iteration":424,"passed_time":1.329430915,"remaining_time":0.2346054555},
{"learn":[0.1770724876],"iteration":425,"passed_time":1.332295312,"remaining_time":0.23143158},
{"learn":[0.1768110313],"iteration":426,"passed_time":1.335201068,"remaining_time":0.2282662247},
{"learn":[0.1764815274],"iteration":427,"passed_time":1.338013529,"remaining_time":0.2250863881},
{"learn":[0.1761686288],"iteration":428,"passed_time":1.340835954,"remaining_time":0.2219099131},
{"learn":[0.1757487877],"iteration":429,"passed_time":1.343797049,"remaining_time":0.2187576591},
{"learn":[0.1751039542],"iteration":430,"passed_time":1.346738258,"remaining_time":0.2156031085},
{"learn":[0.1747797798],"iteration":431,"passed_time":1.349701877,"remaining_time":0.2124530732},
{"learn":[0.1743715137],"iteration":432,"passed_time":1.352635889,"remaining_time":0.2092993177},
{"learn":[0.1742781471],"iteration":433,"passed_time":1.356088883,"remaining_time":0.2062254983},
{"learn":[0.1739867528],"iteration":434,"passed_time":1.359359831,"remaining_time":0.2031227334},
{"learn":[0.173914498],"iteration":435,"passed_time":1.362289198,"remaining_time":0.1999690565},
{"learn":[0.1735881731],"iteration":436,"passed_time":1.365041407,"remaining_time":0.1967908665},
{"learn":[0.1732159035],"iteration":437,"passed_time":1.367971414,"remaining_time":0.1936397892},
{"learn":[0.1728974885],"iteration":438,"passed_time":1.370778861,"remaining_time":0.1904726892},
{"learn":[0.1726470461],"iteration":439,"passed_time":1.373675131,"remaining_time":0.1873193361},
{"learn":[0.172222287],"iteration":440,"passed_time":1.376566995,"remaining_time":0.1841665594},
{"learn":[0.1719647015],"iteration":441,"passed_time":1.379497484,"remaining_time":0.1810200318},
{"learn":[0.1716440425],"iteration":442,"passed_time":1.382789778,"remaining_time":0.1779210323},
{"learn":[0.1713444953],"iteration":443,"passed_time":1.385528742,"remaining_time":0.1747513729},
{"learn":[0.1712044361],"iteration":444,"passed_time":1.388474095,"remaining_time":0.1716091578},
{"learn":[0.1709536758],"iteration":445,"passed_time":1.391216255,"remaining_time":0.1684432237},
{"learn":[0.1705403421],"iteration":446,"passed_time":1.394691712,"remaining_time":0.1653661314},
{"learn":[0.1703592936],"iteration":447,"passed_time":1.398205409,"remaining_time":0.1622916993},
{"learn":[0.1701192108],"iteration":448,"passed_time":1.401258064,"remaining_time":0.1591629427},
{"learn":[0.1697426216],"iteration":449,"passed_time":1.404116602,"remaining_time":0.1560129558},
{"learn":[0.1696113512],"iteration":450,"passed_time":1.40704019,"remaining_time":0.1528713288},
{"learn":[0.1691783643],"iteration":451,"passed_time":1.410061603,"remaining_time":0.1497410552},
{"learn":[0.1689360375],"iteration":452,"passed_time":1.413471796,"remaining_time":0.1466515991},
{"learn":[0.1685641046],"iteration":453,"passed_time":1.41697887,"remaining_time":0.1435705463},
{"learn":[0.1683312958],"iteration":454,"passed_time":1.420744059,"remaining_time":0.1405131487},
{"learn":[0.1681784462],"iteration":455,"passed_time":1.424141539,"remaining_time":0.1374171661},
{"learn":[0.1678963829],"iteration":456,"passed_time":1.427488055,"remaining_time":0.1343150687},
{"learn":[0.1676666409],"iteration":457,"passed_time":1.430830514,"remaining_time":0.1312115319},
{"learn":[0.1673807256],"iteration":458,"passed_time":1.433972913,"remaining_time":0.1280890837},
{"learn":[0.1672548967],"iteration":459,"passed_time":1.436884121,"remaining_time":0.1249464453},
{"learn":[0.1669644374],"iteration":460,"passed_time":1.439831549,"remaining_time":0.1218078751},
{"learn":[0.1666787091],"iteration":461,"passed_time":1.44303537,"remaining_time":0.1186912209},
{"learn":[0.166374674],"iteration":462,"passed_time":1.445805231,"remaining_time":0.1155395109},
{"learn":[0.1662605697],"iteration":463,"passed_time":1.448855906,"remaining_time":0.1124112341},
{"learn":[0.1659023435],"iteration":464,"passed_time":1.451836841,"remaining_time":0.1092780418},
{"learn":[0.1655412001],"iteration":465,"passed_time":1.454708816,"remaining_time":0.1061375531},
{"learn":[0.1652905333],"iteration":466,"passed_time":1.45741934,"remaining_time":0.1029868056},
{"learn":[0.1649766249],"iteration":467,"passed_time":1.4602615,"remaining_time":0.09984694017},
{"learn":[0.1647302964],"iteration":468,"passed_time":1.463132238,"remaining_time":0.09671023318},
{"learn":[0.1645869835],"iteration":469,"passed_time":1.466114618,"remaining_time":0.09358178412},
{"learn":[0.1642218384],"iteration":470,"passed_time":1.468924723,"remaining_time":0.09044334815},
{"learn":[0.1638852475],"iteration":471,"passed_time":1.471805545,"remaining_time":0.08731049842},
{"learn":[0.1634005752],"iteration":472,"passed_time":1.474769693,"remaining_time":0.08418347086},
{"learn":[0.1631198584],"iteration":473,"passed_time":1.477634962,"remaining_time":0.08105170678},
{"learn":[0.1628895928],"iteration":474,"passed_time":1.480504443,"remaining_time":0.07792128647},
{"learn":[0.1625761892],"iteration":475,"passed_time":1.484266251,"remaining_time":0.07483695382},
{"learn":[0.1623009326],"iteration":476,"passed_time":1.488185585,"remaining_time":0.0717573762},
{"learn":[0.1619869307],"iteration":477,"passed_time":1.4914269,"remaining_time":0.06864307908},
{"learn":[0.1617138246],"iteration":478,"passed_time":1.494306661,"remaining_time":0.0655124006},
{"learn":[0.1616542667],"iteration":479,"passed_time":1.497155815,"remaining_time":0.06238149229},
{"learn":[0.1614803426],"iteration":480,"passed_time":1.500421183,"remaining_time":0.0592681964},
{"learn":[0.1611151976],"iteration":481,"passed_time":1.503422342,"remaining_time":0.05614440281},
{"learn":[0.1609694537],"iteration":482,"passed_time":1.50629375,"remaining_time":0.05301655021},
{"learn":[0.1607692569],"iteration":483,"passed_time":1.509546992,"remaining_time":0.04990237989},
{"learn":[0.1605382807],"iteration":484,"passed_time":1.512398263,"remaining_time":0.04677520402},
{"learn":[0.1602731032],"iteration":485,"passed_time":1.515348714,"remaining_time":0.04365202056},
{"learn":[0.1601151111],"iteration":486,"passed_time":1.518412797,"remaining_time":0.04053257979},
{"learn":[0.1599087061],"iteration":487,"passed_time":1.521183322,"remaining_time":0.03740614727},
{"learn":[0.1596412659],"iteration":488,"passed_time":1.52406835,"remaining_time":0.0342837461},
{"learn":[0.1594468285],"iteration":489,"passed_time":1.526882457,"remaining_time":0.03116086647},
{"learn":[0.1591643913],"iteration":490,"passed_time":1.529794432,"remaining_time":0.02804103847},
{"learn":[0.158928572],"iteration":491,"passed_time":1.53278049,"remaining_time":0.02492326},
{"learn":[0.1586653392],"iteration":492,"passed_time":1.535936358,"remaining_time":0.021808427},
{"learn":[0.1584491917],"iteration":493,"passed_time":1.539175799,"remaining_time":0.0186944429},
{"learn":[0.158188876],"iteration":494,"passed_time":1.542708627,"remaining_time":0.01558291542},
{"learn":[0.1579465679],"iteration":495,"passed_time":1.546812401,"remaining_time":0.01247429355},
{"learn":[0.1578339595],"iteration":496,"passed_time":1.550317796,"remaining_time":0.009358055105},
{"learn":[0.1577745699],"iteration":497,"passed_time":1.553283093,"remaining_time":0.006238084709},
{"learn":[0.1575948304],"iteration":498,"passed_time":1.556701583,"remaining_time":0.003119642452},
{"learn":[0.1572537142],"iteration":499,"passed_time":1.560241382,"remaining_time":0}
]}